aevoo_shell/README
aevoo_shell/__init__.py
aevoo_shell/configshell/__init__.py
aevoo_shell/configshell/confignode.py
aevoo_shell/configshell/log.py
aevoo_shell/configshell/shell.py
aevoo_shell/configshell-fb/.git/COMMIT_EDITMSG
aevoo_shell/configshell-fb/.git/FETCH_HEAD
aevoo_shell/configshell-fb/.git/HEAD
aevoo_shell/configshell-fb/.git/ORIG_HEAD
aevoo_shell/configshell-fb/.git/config
aevoo_shell/configshell-fb/.git/description
aevoo_shell/configshell-fb/.git/hooks/applypatch-msg.sample
aevoo_shell/configshell-fb/.git/hooks/commit-msg.sample
aevoo_shell/configshell-fb/.git/hooks/fsmonitor-watchman.sample
aevoo_shell/configshell-fb/.git/hooks/post-update.sample
aevoo_shell/configshell-fb/.git/hooks/pre-applypatch.sample
aevoo_shell/configshell-fb/.git/hooks/pre-commit.sample
aevoo_shell/configshell-fb/.git/hooks/pre-merge-commit.sample
aevoo_shell/configshell-fb/.git/hooks/pre-push.sample
aevoo_shell/configshell-fb/.git/hooks/pre-rebase.sample
aevoo_shell/configshell-fb/.git/hooks/pre-receive.sample
aevoo_shell/configshell-fb/.git/hooks/prepare-commit-msg.sample
aevoo_shell/configshell-fb/.git/hooks/push-to-checkout.sample
aevoo_shell/configshell-fb/.git/hooks/sendemail-validate.sample
aevoo_shell/configshell-fb/.git/hooks/update.sample
aevoo_shell/configshell-fb/.git/index
aevoo_shell/configshell-fb/.git/info/exclude
aevoo_shell/configshell-fb/.git/logs/HEAD
aevoo_shell/configshell-fb/.git/logs/refs/heads/async-implementation
aevoo_shell/configshell-fb/.git/logs/refs/heads/master
aevoo_shell/configshell-fb/.git/logs/refs/remotes/origin/HEAD
aevoo_shell/configshell-fb/.git/logs/refs/remotes/origin/async-implementation
aevoo_shell/configshell-fb/.git/logs/refs/remotes/origin/fix-log
aevoo_shell/configshell-fb/.git/logs/refs/remotes/origin/main
aevoo_shell/configshell-fb/.git/logs/refs/remotes/origin/master
aevoo_shell/configshell-fb/.git/objects/00/225d277de5a72868214f844d3bef12c54504f2
aevoo_shell/configshell-fb/configshell_fb.egg-info/PKG-INFO
aevoo_shell/configshell-fb/configshell_fb.egg-info/SOURCES.txt
aevoo_shell/configshell-fb/configshell_fb.egg-info/dependency_links.txt
aevoo_shell/configshell-fb/configshell_fb.egg-info/requires.txt
aevoo_shell/configshell-fb/configshell_fb.egg-info/top_level.txt
aevoo_shell-0.1.1.dist-info/METADATA
aevoo_shell-0.1.1.dist-info/WHEEL
aevoo_shell-0.1.1.dist-info/entry_points.txt
aevoo_shell-0.1.1.dist-info/RECORD
